MANIFEST.in
readme.mkd
setup.py
examples/generate_traffic.py
examples/gunicorn.conf.py
gstats/__init__.py
gstats/wsgi.py
gstats.egg-info/PKG-INFO
gstats.egg-info/SOURCES.txt
gstats.egg-info/dependency_links.txt
gstats.egg-info/top_level.txt
munin/gunicorn-request-time_
munin/gunicorn-requests_
scripts/gstats-collectd
scripts/gstatsctl