Metadata-Version: 1.1
Name: gstats
Version: 0.6.1
Summary: Flexible statistics gathering application, initially built for gunicorn (hence the g)
Home-page: https://github.com/m0n5t3r/gstats
Author: Sabin Iacob
Author-email: iacobs+gst@m0n5t3r.info
License: UNKNOWN
Download-URL: https://github.com/m0n5t3r/gstats
Platform: UNKNOWN
Classifier: Development Status :: 4 - Beta
Classifier: Environment :: Console
Classifier: Environment :: Web Environment
Classifier: Intended Audience :: Developers
Classifier: Intended Audience :: System Administrators
Classifier: License :: OSI Approved :: MIT License
Classifier: Operating System :: POSIX :: Linux
Classifier: Programming Language :: Python
Classifier: Topic :: System :: Monitoring
Classifier: Topic :: System :: Logging
Classifier: Topic :: Internet
Requires: pyzmq(>=2.0)
